biosimulators_copasi/__init__.py
biosimulators_copasi/__main__.py
biosimulators_copasi/_version.py
biosimulators_copasi/core.py
biosimulators_copasi/data_model.py
biosimulators_copasi/utils.py
biosimulators_copasi-0.2.23.dist-info/LICENSE
biosimulators_copasi-0.2.23.dist-info/METADATA
biosimulators_copasi-0.2.23.dist-info/WHEEL
biosimulators_copasi-0.2.23.dist-info/entry_points.txt
biosimulators_copasi-0.2.23.dist-info/RECORD
