Metadata-Version: 2.1
Name: biosimulators-copasi
Version: 0.2.23
Summary: BioSimulators-compliant command-line interface to the COPASI simulation program <http://copasi.org>.
Home-page: https://basico.readthedocs.io/en/latest/
License: MIT
Keywords: systems,biology,modeling,simulation
Author: Center for Reproducible Biomedical Modeling
Author-email: info@biosimulators.org
Requires-Python: >=3.10,<4.0
Classifier: Development Status :: 3 - Alpha
Classifier: Intended Audience :: Science/Research
Classifier: License :: OSI Approved :: MIT License
Classifier: Programming Language :: Python :: 3
Classifier: Programming Language :: Python :: 3.10
Classifier: Programming Language :: Python :: 3.11
Classifier: Programming Language :: Python :: 3.12
Classifier: Topic :: Scientific/Engineering :: Bio-Informatics
Requires-Dist: biosimulators_utils[logging,sbml] (>=0.2.2,<0.3.0)
Requires-Dist: cement (>=3.0.8,<4.0.0)
Requires-Dist: copasi_basico (>=0.80)
Requires-Dist: docker (>=7.1.0,<8.0.0)
Requires-Dist: evalidate (>=2.0.1,<3.0.0)
Requires-Dist: kisao (>=2.34,<3.0)
Requires-Dist: lxml (>=4.9.2,<5.0.0)
Requires-Dist: numpy (>=1.24.4,<2.0.0)
Requires-Dist: pandas (>=2.0.2,<3.0.0)
Requires-Dist: python-copasi (>=4.45.296)
Requires-Dist: python_dateutil (>=2.8.2,<3.0.0)
Requires-Dist: python_libsbml (>=5.20.1,<6.0.0)
Requires-Dist: setuptools (>=75.1.0,<76.0.0)
Requires-Dist: termcolor (>=2.3.0,<3.0.0)
Project-URL: Repository, https://github.com/biosimulators/Biosimulators_COPASI
